LICENSE.txt
README.md
cli/__init__.py
cli/azkv.py
cli/client/__init__.py
cli/client/keyvault_client.py
cli/client/keyvault_clients.py
cli/client/keyvault_secret.py
cli/commands/__init__.py
cli/commands/check.py
cli/commands/common.py
cli/commands/edit.py
cli/commands/show.py
cli/commands/vaults/__init__.py
cli/commands/vaults/add.py
cli/commands/vaults/login.py
cli/commands/vaults/main.py
cli/commands/vaults/remove.py
cli/commands/vaults/select.py
cli/decorators.py
cli/main.py
pyproject.toml
azure_keyvault_cli-0.3.3.dist-info/LICENSE.txt
azure_keyvault_cli-0.3.3.dist-info/METADATA
azure_keyvault_cli-0.3.3.dist-info/WHEEL
azure_keyvault_cli-0.3.3.dist-info/entry_points.txt
azure_keyvault_cli-0.3.3.dist-info/RECORD
