Metadata-Version: 2.1
Name: azure-keyvault-cli
Version: 0.3.3
Summary: This is a CLI to show and check secrets from an Azure KeyVault
Home-page: https://github.com/mkah91/azure-keyvault-cli
License: MIT
Keywords: azure,keyvault,cli,secrets
Author: mkah91
Author-email: marius_knepper@web.de
Requires-Python: >=3.9,<4.0
Classifier: License :: OSI Approved :: MIT License
Classifier: Programming Language :: Python :: 3
Classifier: Programming Language :: Python :: 3.9
Classifier: Programming Language :: Python :: 3.10
Classifier: Programming Language :: Python :: 3.11
Classifier: Programming Language :: Python :: 3.12
Requires-Dist: azure-identity (>=1.14.1,<2.0.0)
Requires-Dist: azure-keyvault-secrets (>=4.7.0,<5.0.0)
Requires-Dist: click (>=8.1.3,<9.0.0)
Requires-Dist: halo (>=0.0.31,<0.0.32)
Requires-Dist: inquirerpy (>=0.3.4,<0.4.0)
Requires-Dist: pydantic (>=1.10.7,<2.0.0)
Requires-Dist: pyperclip (>=1.8.2,<2.0.0)
Requires-Dist: toml (>=0.10.0,<0.11.0)
Project-URL: Repository, https://github.com/mkah91/azure-keyvault-cli
